github_contexts/__init__.py
github_contexts/_util.py
github_contexts/property_dict.py
github_contexts/github/__init__.py
github_contexts/github/context.py
github_contexts/github/enum.py
github_contexts/github/payload/__init__.py
github_contexts/github/payload/base.py
github_contexts/github/payload/issue_comment.py
github_contexts/github/payload/issues.py
github_contexts/github/payload/pull_request.py
github_contexts/github/payload/push.py
github_contexts/github/payload/schedule.py
github_contexts/github/payload/workflow_dispatch.py
github_contexts/github/payload/object/__init__.py
github_contexts/github/payload/object/auto_merge.py
github_contexts/github/payload/object/changes.py
github_contexts/github/payload/object/comment.py
github_contexts/github/payload/object/commit.py
github_contexts/github/payload/object/commit_author.py
github_contexts/github/payload/object/head_base.py
github_contexts/github/payload/object/issue.py
github_contexts/github/payload/object/label.py
github_contexts/github/payload/object/license.py
github_contexts/github/payload/object/milestone.py
github_contexts/github/payload/object/performed_via_github_app.py
github_contexts/github/payload/object/permissions.py
github_contexts/github/payload/object/pull_request.py
github_contexts/github/payload/object/reactions.py
github_contexts/github/payload/object/repository.py
github_contexts/github/payload/object/team.py
github_contexts/github/payload/object/user.py
github_contexts-0.1.1.dist-info/METADATA
github_contexts-0.1.1.dist-info/WHEEL
github_contexts-0.1.1.dist-info/top_level.txt
github_contexts-0.1.1.dist-info/RECORD
