Metadata-Version: 2.4
Name: GitHub-Contexts
Version: 0.1.1
Requires-Python: >=3.10
Requires-Dist: ruamel.yaml<0.19,>=0.17
Requires-Dist: ruamel.yaml.string<0.2,>=0.1
